{"count":34,"routes":[{"endpoint":"static","methods":["GET"],"rule":"/<path:filename>"},{"endpoint":"auth_bp.whoami","methods":["GET"],"rule":"/auth/whoami"},{"endpoint":"routes.index","methods":["GET"],"rule":"/"},{"endpoint":"routes.processar_audio","methods":["POST"],"rule":"/audio"},{"endpoint":"routes.ping","methods":["GET"],"rule":"/ping"},{"endpoint":"teste_eleven_route.teste_eleven","methods":["GET"],"rule":"/teste-eleven"},{"endpoint":"licencas.ativar_cupom_compat_v2","methods":["POST"],"rule":"/licencas/ativar-cupom"},{"endpoint":"captcha_bp.verify_captcha","methods":["POST"],"rule":"/captcha/verify"},{"endpoint":"config.salvar_configuracao","methods":["POST"],"rule":"/api/configuracao"},{"endpoint":"importar_precos.importar_precos","methods":["POST"],"rule":"/api/importar-precos"},{"endpoint":"seed_bp.seed_profissional","methods":["POST"],"rule":"/_seed/profissional"},{"endpoint":"seed_bp.seed_precos","methods":["POST"],"rule":"/_seed/precos"},{"endpoint":"bp_webhook.verify_webhook","methods":["GET"],"rule":"/webhook"},{"endpoint":"bp_webhook.receive_webhook","methods":["POST"],"rule":"/webhook"},{"endpoint":"health","methods":["GET"],"rule":"/health"},{"endpoint":"list_routes","methods":["GET"],"rule":"/__routes"},{"endpoint":"__wa_debug","methods":["GET"],"rule":"/__wa_debug"},{"endpoint":"env_safe","methods":["GET"],"rule":"/__env_safe"},{"endpoint":"ping_firestore","methods":["GET"],"rule":"/__ping_firestore"},{"endpoint":"debug_doc","methods":["GET"],"rule":"/__doc"},{"endpoint":"debug_list","methods":["GET"],"rule":"/__list"},{"endpoint":"wa_bot_status","methods":["GET"],"rule":"/__wa_bot_status"},{"endpoint":"api_send_text","methods":["GET","POST"],"rule":"/api/send-text"},{"endpoint":"msisdn_debug","methods":["GET"],"rule":"/__msisdn_debug"},{"endpoint":"_preflight_api_cupons_validar_publico","methods":[],"rule":"/api/cupons/validar-publico"},{"endpoint":"api_cupons_validar_publico","methods":["POST"],"rule":"/api/cupons/validar-publico"},{"endpoint":"_preflight_api_cupons_ativar","methods":[],"rule":"/api/cupons/ativar"},{"endpoint":"api_cupons_ativar","methods":["POST"],"rule":"/api/cupons/ativar"},{"endpoint":"_preflight_api_cupons_ativar_legado","methods":[],"rule":"/api/cupons/ativar-cupom"},{"endpoint":"api_cupons_ativar_legado","methods":["POST"],"rule":"/api/cupons/ativar-cupom"},{"endpoint":"goto_ativar","methods":["GET"],"rule":"/ativar"},{"endpoint":"index","methods":["GET"],"rule":"/"},{"endpoint":"static_proxy","methods":["GET"],"rule":"/<path:path>"},{"endpoint":"server_whoami","methods":["GET"],"rule":"/__whoami"}]}
